setup.py
logic.egg-info/PKG-INFO
logic.egg-info/SOURCES.txt
logic.egg-info/dependency_links.txt
logic.egg-info/not-zip-safe
logic.egg-info/requires.txt
logic.egg-info/top_level.txt
logpy/__init__.py
logpy/arith.py
logpy/assoccomm.py
logpy/core.py
logpy/dispatch.py
logpy/facts.py
logpy/goals.py
logpy/term.py
logpy/unification.py
logpy/unifymore.py
logpy/util.py
logpy/variable.py