Metadata-Version: 1.0
Name: logic
Version: 0.2.1
Summary: Logic Programming in python
Home-page: http://github.com/logpy/logpy
Author: Matthew Rocklin
Author-email: mrocklin@gmail.com
License: BSD
Platform: UNKNOWN
